README.md
setup.py
ag_cc_proxy.egg-info/PKG-INFO
ag_cc_proxy.egg-info/SOURCES.txt
ag_cc_proxy.egg-info/dependency_links.txt
ag_cc_proxy.egg-info/entry_points.txt
ag_cc_proxy.egg-info/requires.txt
ag_cc_proxy.egg-info/top_level.txt
antigravity_proxy/__init__.py
antigravity_proxy/__main__.py
antigravity_proxy/accounts.py
antigravity_proxy/auth.py
antigravity_proxy/cli.py
antigravity_proxy/cloudcode.py
antigravity_proxy/config.py
antigravity_proxy/converter.py
antigravity_proxy/py.typed
antigravity_proxy/server.py
tests/__init__.py