Metadata-Version: 2.4
Name: ag-cc-proxy
Version: 0.1.0
Summary: Proxy for Antigravity Claude/Gemini models with Claude Code CLI
Home-page: https://github.com/TutraLabs/ag-cc-proxy
Author: Catalyst
Author-email: tutralabs@gmail.com
License: MIT
Classifier: Programming Language :: Python :: 3
Classifier: Programming Language :: Python :: 3.10
Classifier: Programming Language :: Python :: 3.11
Classifier: Programming Language :: Python :: 3.12
Classifier: Operating System :: OS Independent
Requires-Python: >=3.10
Requires-Dist: aiohttp>=3.9.0
Dynamic: author
Dynamic: author-email
Dynamic: classifier
Dynamic: description
Dynamic: description-content-type
Dynamic: home-page
Dynamic: license
Dynamic: requires-dist
Dynamic: requires-python
Dynamic: summary
